[
	
	{
		"id": 1,
		"name": "Apple",
		"price": 40,
		"quantity": 0,
		"image": "apple.jpg"		
	},
	{
		"id": 2,
		"name": "Banana",
		"price": 50,
		"quantity": 0,
		"image": "banana.jpg"
	},
	{
		"id": 3,
		"name": "Cherry",
		"price": 80,
		"quantity": 0,
		"image": "cherry.jpg"
	},
	{
		"id": 4,
		"name": "Coconut",
		"price": 100,
		"quantity": 0,
		"image": "coconut.jpg"
	},
	{
		"id": 5,
		"name": "Cranberry",
		"price": 120,
		"quantity": 0,
		"image": "cranberry.jpg"
	},
	{
		"id": 6,
		"name": "Guava",
		"price": 50,
		"quantity": 0,
		"image": "guava.jpg"
	},
	{
		"id": 7,
		"name": "Grape",
		"price": 40,
		"quantity": 0,
		"image": "grape.jpg"
	},
	{
		"id": 8,
		"name": "Mango",
		"price": 120,
		"quantity": 0,
		"image": "mango.jpg"
	},
	{
		"id": 9,
		"name": "Lemon",
		"price": 10,
		"quantity": 0,
		"image": "lemon.jpg"
	},
	{
		"id": 10,
		"name": "Orange",
		"price": 70,
		"quantity": 0,
		"image": "orange.png"
	},
	{
		"id": 11,
		"name": "Papaya",
		"price": 90,
		"quantity": 0,
		"image": "papaya.jpg"
	},
	{
		"id": 12,
		"name": "Plum",
		"price": 60,
		"quantity": 0,
		"image": "plum.jpg"
	},
	{
		"id": 13,
		"name": "Pineapple",
		"price": 140,
		"quantity": 0,
		"image": "pineapple.jpg"
	},
	{
		"id": 14,
		"name": "Strawberry",
		"price": 160,
		"quantity": 0,
		"image": "strawberry.jpg"
	},
	{
		"id": 15,
		"name": "Watermelon",
		"price": 75,
		"quantity": 0,
		"image": "watermelon.jpg"
	}

]

